CHANGELOG
LICENSE
MANIFEST.in
README.rst
pip.conf
requirements.txt
sample_config
setup.cfg
setup.py
soundmeter/__init__.py
soundmeter/cli.py
soundmeter/meter.py
soundmeter/monitor.py
soundmeter/settings.py
soundmeter/tests.py
soundmeter/utils.py
soundmeter.egg-info/PKG-INFO
soundmeter.egg-info/SOURCES.txt
soundmeter.egg-info/dependency_links.txt
soundmeter.egg-info/entry_points.txt
soundmeter.egg-info/not-zip-safe
soundmeter.egg-info/requires.txt
soundmeter.egg-info/top_level.txt