Metadata-Version: 1.1
Name: soundmeter
Version: 0.1.3
Summary: Simple real-time sound meter.
Home-page: https://github.com/shichao-an/soundmeter
Author: Shichao An
Author-email: shichao.an@nyu.edu
License: BSD
Keywords: soundmeter
Platform: UNKNOWN
Classifier: Environment :: Console
Classifier: License :: OSI Approved :: BSD License
Classifier: Programming Language :: Python
Classifier: Programming Language :: Python :: 2
